document_template/__init__.py
document_template/template.py
document_template-1.1.0.dist-info/LICENSE
document_template-1.1.0.dist-info/METADATA
document_template-1.1.0.dist-info/WHEEL
document_template-1.1.0.dist-info/top_level.txt
document_template-1.1.0.dist-info/RECORD
