Metadata-Version: 2.1
Name: document-template
Version: 1.1.0
Summary: Generate documents from templates.
Home-page: https://github.com/liying2008/document-template
Author: liying
Author-email: liruoer2008@yeah.net
Maintainer: liying
Maintainer-email: liruoer2008@yeah.net
License: MIT
Project-URL: Documentation, https://github.com/liying2008/document-template
Project-URL: Source, https://github.com/liying2008/document-template
Keywords: template document parser
Classifier: Environment :: Console
Classifier: Intended Audience :: Developers
Classifier: Intended Audience :: Information Technology
Classifier: License :: OSI Approved :: MIT License
Classifier: Operating System :: OS Independent
Classifier: Programming Language :: Python :: 2.7
Classifier: Programming Language :: Python :: 3
Classifier: Topic :: Utilities
License-File: LICENSE
